wg_wizard/__init__.py
wg_wizard/__main__.py
wg_wizard/cli.py
wg_wizard/core.py
wg_wizard/paths.py
wg_wizard/utils.py
wg_wizard/wg.py
wg_wizard/wg_quick.py
wg_wizard-0.3.0.dist-info/LICENSE
wg_wizard-0.3.0.dist-info/METADATA
wg_wizard-0.3.0.dist-info/WHEEL
wg_wizard-0.3.0.dist-info/entry_points.txt
wg_wizard-0.3.0.dist-info/RECORD
