Metadata-Version: 2.1
Name: wg-wizard
Version: 0.3.0
Summary: Control all the WireGuard server and client configs in a centralized way.
Home-page: https://github.com/ianlini/wg-wizard
License: MIT
Author: Ian Lin
Author-email: you@example.com
Requires-Python: >=3.10,<4.0
Classifier: License :: OSI Approved :: MIT License
Classifier: Programming Language :: Python :: 3
Classifier: Programming Language :: Python :: 3.10
Classifier: Programming Language :: Python :: 3.11
Classifier: Topic :: Security
Classifier: Topic :: Utilities
Requires-Dist: click (>=8.1.3,<9.0.0)
Requires-Dist: pydantic (>=2.0.0,<3.0.0)
Requires-Dist: qrcode (>=7.3.1,<8.0.0)
Requires-Dist: ruamel.yaml (>=0.17.21,<0.18.0)
Project-URL: Repository, https://github.com/ianlini/wg-wizard
